[
  {
    "label": "ECirculation",
    "lastest": "0.03Bate",
    "updateTime": 20221207,
    "lowest": "0.03Bate",
    "review": [
      "0.02Bate",
      "0.03Bate"
    ]
  },
  {
    "label": "sunshine",
    "lastest": "0.01Bate",
    "updateTime": 20230223,
    "lowest": "0.01Bate",
    "review": []
  },
  {
    "label": "consume",
    "lastest": "0.01Bate",
    "updateTime": 20220513,
    "lowest": "0.01Bate"
  },
  {
    "label": "ble",
    "lastest": "1.0.20",
    "updateTime": 20220513,
    "lowest": "1.0.20"
  }
]